netbox_network_diagram/__init__.py
netbox_network_diagram/navigation.py
netbox_network_diagram/urls.py
netbox_network_diagram/views.py
netbox_network_diagram/api/__init__.py
netbox_network_diagram/migrations/__init__.py
netbox_network_diagram/static/netbox_network_diagram/css/style.css
netbox_network_diagram/static/netbox_network_diagram/img/ix.png
netbox_network_diagram/static/netbox_network_diagram/img/nat.png
netbox_network_diagram/static/netbox_network_diagram/img/router.png
netbox_network_diagram/static/netbox_network_diagram/img/switch.png
netbox_network_diagram/static/netbox_network_diagram/js/cola.min.js
netbox_network_diagram/static/netbox_network_diagram/js/inet-henge.min.js
netbox_network_diagram/templates/netbox_network_diagram/index.html
netbox_network_diagram-0.1.2.dist-info/LICENSE
netbox_network_diagram-0.1.2.dist-info/METADATA
netbox_network_diagram-0.1.2.dist-info/WHEEL
netbox_network_diagram-0.1.2.dist-info/top_level.txt
netbox_network_diagram-0.1.2.dist-info/RECORD
